<?xml version="1.0" encoding="utf-8" standalone="yes"?>
<hmpReleaseInfo.xml>

  <uk>
    <enabled>true</enabled>
    <version>1.0.47</version>
                              
    <changes>
Версія #1.0.47, від 16.01.2026:
                  • Оновлено для патча 2.1.1.0.  
                  1) ОНОВЛЕНО ПРИЦІЛИ:
                     ВСІ, ОКРІМ: ЗМЕНШЕНЕ КОЛО ТА КРОСХАЇРС 
                  2) ОНОВЛЕНО: 
                     ЗОЛОТІ ІКОНКИ ПРЕМ ТЕХНІКИ ТА СПЕЦ
                     МЕНЕДЖЕР АНГАРІВ
                     ЗАМІНА ІКОНОК СССР В ГАРАЖІ
                     АВТОЗБІР ПОХОДУ 
                     ТОПОГРАФІЧНІ МАПИ
                     ТАКТИЧНІ МАПИ ( КУДИ СТАВАТИ ТЕХНІЦІ РІЗНИХ КЛАСІВ )
                     3Д СТИЛІ
                     КОЛЬОРОВІ ІКОНКИ
                     СВІТЛОФОР
                     ХП У ВУХАХ КОМАНД БЕЗ ХВМ
                     ВН 8 БЕЗ ХВМ
                     ОБЛАДНАННЯ В БОЮ
                     РЕМОНТ В КІНЦІ БОЮ
                     ДЕМОНТАЖ ОБЛАДНАННЯ 
                 
                     
                     
                  
                       
                     
                        
                         
            
            

    </changes>
    <forumTheme></forumTheme>
    <downloadLink>https://habwotmods.pp.ua/</downloadLink>
    <modsBlackList>
    </modsBlackList>
    <xvm>
      <isReleaseAvailable>False</isReleaseAvailable>
      <releaseVersionURL>https://dl1.modxvm.com/release/xvm_10.2.1.zip</releaseVersionURL>
      <nightlyVersionURL>https://nightly.modxvm.com/download/master/xvm_latest.zip</nightlyVersionURL>
    </xvm>
  </uk>

  <en>
    <enabled>true</enabled>
    <version>1.0.47</version>
    <changes>
Version #1.0.47, date 16.01.2026:
 • updated: patch 1.0.47.
                            🔧 UPDATE
🎯 Crosshairs

All crosshairs updated

❌ Exceptions: reduced circle and crosshair

🆕 Added & Updated

Gold icons for premium and special vehicles
Hangar manager
Replacement of USSR icons in the garage
Campaign auto-collection
Topographic maps
Tactical maps
(recommended positions for different vehicle classes)
3D styles
Colored icons
Traffic light system
Team HP display without XVM
WN8 without XVM
Equipment display in battle
Repair at the end of battle
Equipment demounting

    </changes>
    <forumTheme></forumTheme>
    <downloadLink>https://habwotmods.pp.ua/</downloadLink>
    <modsBlackList>
    </modsBlackList>
    <xvm>
      <isReleaseAvailable>False</isReleaseAvailable>
      <releaseVersionURL>https://dl1.modxvm.com/release/xvm_10.2.1.zip</releaseVersionURL>
      <nightlyVersionURL>https://nightly.modxvm.com/download/master/xvm_latest.zip</nightlyVersionURL>
    </xvm>
  </en>

  <ru>
    <enabled>true</enabled>
    <version>1.0.47</version>
    <changes>
Версия #1.0.47 от 16.01.2026:
   • Сборка обновлена для 2.1.1.0.

                   🔧 ОБНОВЛЕНИЕ
🎯 Прицелы

Обновлены все прицелы

❌ Исключения: уменьшенный круг и кроссхайр
🆕 Добавлено и обновлено
Золотые иконки премиум и специальной техники
Менеджер ангаров
Замена иконок СССР в гараже
Автосбор кампании
Топографические карты
Тактические карты
(рекомендации по позициям для техники разных классов)
3D-стили
Цветные иконки
Светофор
HP в «ушах» команд без XVM
WN8 без XVM
Отображение оборудования в бою
Ремонт в конце боя
Демонтаж оборудования


    </changes> 
    <forumTheme></forumTheme>
    <downloadLink>https://habwotmods.pp.ua/</downloadLink>
    <modsBlackList>
    </modsBlackList>
    <xvm>
      <isReleaseAvailable>False</isReleaseAvailable>
      <releaseVersionURL>https://dl1.modxvm.com/release/xvm_10.2.1.zip</releaseVersionURL>
      <nightlyVersionURL>https://nightly.modxvm.com/download/master/xvm_latest.zip</nightlyVersionURL>
    </xvm>
  </ru>

<infoPanel>
  <title>Деталі оновлення</title>
  <wheelInfo>
    <item label="Версія мода" value="5.8"/>
    <item label="Патч гри" value="1.29.1.0"/>
    <item label="Стан" value="Доступно оновлення"/>
    <item label="Сайт" value="habwotmods.pp.ua"/>
  </wheelInfo>
</infoPanel>

</hmpReleaseInfo.xml>

